kalman_filter/gyro.py
py_sensor_filters-0.1.1.post1.dist-info/LICENSE
py_sensor_filters-0.1.1.post1.dist-info/METADATA
py_sensor_filters-0.1.1.post1.dist-info/WHEEL
py_sensor_filters-0.1.1.post1.dist-info/top_level.txt
py_sensor_filters-0.1.1.post1.dist-info/RECORD
