Metadata-Version: 2.1
Name: py-sensor-filters
Version: 0.1.1.post1
Summary: Fast Signal Filters Wrapped in Python
Home-page: https://github.com/underflow101/py_filters
Author: underflow101
Author-email: ikarus125@gmail.com
License: UNKNOWN
Project-URL: Bug Tracker, https://github.com/underflow101/py_filters/issues
Platform: UNKNOWN
Classifier: Programming Language :: Python :: 3
Classifier: License :: OSI Approved :: MIT License
Classifier: Operating System :: OS Independent
Requires-Python: >=3.6
License-File: LICENSE
